{
  "date": "2026-03-06",
  "dateLabel": "3/6(金)",
  "generatedAt": "2026-03-31T08:38:30.029036",
  "selectedMenus": [
    {
      "name": "たらの葱味噌焼き",
      "score": 0.2807029199250559,
      "rank": 1,
      "reasons": [
        "野菜が多い"
      ],
      "nutrition": {
        "エネルギー": 113,
        "たんぱく質": 15.5,
        "脂質": 0.9,
        "炭水化物": 9.3,
        "飽和脂肪酸": 0.04,
        "食塩相当量": 1.7,
        "野菜重量": 32,
        "卵": "－",
        "乳類": "－",
        "小麦": "－",
        "そば": "－",
        "落花生": "－",
        "海老": "－",
        "カニ": "－",
        "牛肉": "－",
        "くるみ": "－",
        "大豆": "◯",
        "鶏肉": "－",
        "豚肉": "－"
      }
    },
    {
      "name": "生姜風味の根菜うどん",
      "score": 0.1138252808087486,
      "rank": 2,
      "reasons": [
        "野菜が多い"
      ],
      "nutrition": {
        "エネルギー": 354,
        "たんぱく質": 10.9,
        "脂質": 5.4,
        "炭水化物": 66,
        "飽和脂肪酸": 1.65,
        "食塩相当量": 4.6,
        "野菜重量": 106,
        "卵": "◯",
        "乳類": "◯",
        "小麦": "◯",
        "そば": "－",
        "落花生": "－",
        "海老": "－",
        "カニ": "－",
        "牛肉": "－",
        "くるみ": "－",
        "大豆": "◯",
        "鶏肉": "◯",
        "豚肉": "◯"
      }
    },
    {
      "name": "キャベツのぺぺロン炒め",
      "score": 0.08757858749765089,
      "rank": 3,
      "reasons": [
        "野菜が多い"
      ],
      "nutrition": {
        "エネルギー": 46,
        "たんぱく質": 2.8,
        "脂質": 2,
        "炭水化物": 5.2,
        "飽和脂肪酸": 0.02,
        "食塩相当量": 0.7,
        "野菜重量": 87,
        "卵": "◯",
        "乳類": "◯",
        "小麦": "◯",
        "そば": "－",
        "落花生": "－",
        "海老": "◯",
        "カニ": "◯",
        "牛肉": "－",
        "くるみ": "－",
        "大豆": "◯",
        "鶏肉": "◯",
        "豚肉": "◯"
      }
    }
  ],
  "allMenusWithScores": [
    {
      "name": "たらの葱味噌焼き",
      "score": 0.2807029199250559,
      "rank": 1
    },
    {
      "name": "生姜風味の根菜うどん",
      "score": 0.1138252808087486,
      "rank": 2
    },
    {
      "name": "キャベツのぺぺロン炒め",
      "score": 0.08757858749765089,
      "rank": 3
    },
    {
      "name": "鶏南蛮そば",
      "score": 0.08335517690904627,
      "rank": 4
    },
    {
      "name": "塩分カット・豚肉の生姜焼",
      "score": 0.07269611949617717,
      "rank": 5
    },
    {
      "name": "ペッパーポーク丼ミニ",
      "score": 0.07044660020098908,
      "rank": 6
    },
    {
      "name": "こんにゃくの炒め煮",
      "score": 0.06455217750497252,
      "rank": 7
    },
    {
      "name": "味噌ラーメン",
      "score": 0.05977598288603972,
      "rank": 8
    },
    {
      "name": "ペッパーポーク丼",
      "score": 0.05655321816809613,
      "rank": 9
    },
    {
      "name": "舞茸としめじのクリームソースオムライス",
      "score": 0.05095210898201168,
      "rank": 10
    },
    {
      "name": "白菜のとろろ昆布和え",
      "score": 0.049912706496207784,
      "rank": 11
    },
    {
      "name": "カレーライスミニ",
      "score": 0.04408820112775773,
      "rank": 12
    },
    {
      "name": "鶏の唐揚げ　ハニーマスタードソース",
      "score": 0.03815372141385269,
      "rank": 13
    },
    {
      "name": "もずくとわかめの酢の物",
      "score": 0.037664691750695034,
      "rank": 14
    },
    {
      "name": "鶏の唐揚げ　ハニーマスタードソースミニ",
      "score": 0.0333492082865031,
      "rank": 15
    },
    {
      "name": "カレーライス",
      "score": 0.030716910191782895,
      "rank": 16
    },
    {
      "name": "かに風味玉子",
      "score": 0.03023608457872028,
      "rank": 17
    },
    {
      "name": "豚肉と茄子のチーズカレー炒め",
      "score": 0.028367531310800765,
      "rank": 18
    },
    {
      "name": "小口ねぎ",
      "score": 0.02146307747821876,
      "rank": 19
    },
    {
      "name": "サクサク衣の牛肉コロッケ",
      "score": 0.017614560956940806,
      "rank": 20
    }
  ],
  "modelInfo": {
    "model": "RandomForest",
    "trainingDays": 15,
    "accuracy": 0.9995,
    "features": {
      "total": 258,
      "nutrition": 13,
      "text": 230,
      "category": 13,
      "cooccurrence": 2
    }
  }
}