{
  "date": "2026-01-26",
  "dayOfWeek": "月",
  "user": "ONO",
  "timestamp": "2026-01-26T03:07:20.019Z",
  "settings": {
    "targets": {},
    "preferences": {}
  },
  "selectedMenus": [
    {
      "name": "極み関西出汁の稲庭風うどん＆ミニうなぎ丼",
      "nutrition": {
        "エネルギー": 803,
        "たんぱく質": 28.9,
        "脂質": 16.7,
        "炭水化物": 132.4,
        "飽和脂肪酸": 4.02,
        "食塩相当量": 4.2,
        "野菜重量": 1,
        "卵": "◯",
        "乳類": "◯",
        "小麦": "◯",
        "そば": "－",
        "落花生": "◯",
        "海老": "◯",
        "カニ": "◯",
        "牛肉": "◯",
        "くるみ": "－",
        "大豆": "◯",
        "鶏肉": "◯",
        "豚肉": "◯"
      }
    },
    {
      "name": "グリーンサラダ(2F)",
      "nutrition": {
        "エネルギー": 15,
        "たんぱく質": 0.6,
        "脂質": 0.5,
        "炭水化物": 2.7,
        "飽和脂肪酸": 0.01,
        "食塩相当量": 0.1,
        "野菜重量": 53,
        "卵": "－",
        "乳類": "－",
        "小麦": "－",
        "そば": "－",
        "落花生": "－",
        "海老": "－",
        "カニ": "－",
        "牛肉": "－",
        "くるみ": "－",
        "大豆": "－",
        "鶏肉": "－",
        "豚肉": "－"
      }
    }
  ],
  "totals": {
    "エネルギー": 818,
    "たんぱく質": 29.5,
    "脂質": 17.2,
    "炭水化物": 135.1,
    "野菜重量": 54
  },
  "achievement": {}
}